Metadata-Version: 1.1
Name: irc-pyhole
Version: 0.8.8
Summary: A modular IRC & Slack bot.
Home-page: https://github.com/jk0/pyhole
Author: Josh Kearney
Author-email: josh@jk0.org
License: UNKNOWN
Platform: UNKNOWN
Classifier: Intended Audience :: Developers
Classifier: Intended Audience :: Information Technology
Classifier: Intended Audience :: System Administrators
Classifier: License :: OSI Approved :: Apache Software License
Classifier: Operating System :: OS Independent
Classifier: Programming Language :: Python
